nums_from_string/__init__.py
nums_from_string/nums_from_string.py
nums_from_string-0.1.1.dist-info/LICENSE
nums_from_string-0.1.1.dist-info/METADATA
nums_from_string-0.1.1.dist-info/WHEEL
nums_from_string-0.1.1.dist-info/top_level.txt
nums_from_string-0.1.1.dist-info/RECORD
