Metadata-Version: 2.1
Name: nums-from-string
Version: 0.1.1
Summary: Extract numbers from a string
Home-page: https://github.com/doubleBite/Numbers-from-String
Author: Shih-hong Tsai
Author-email: doublebite@iis.sinica.edu.tw
License: MIT
Platform: UNKNOWN
Classifier: Programming Language :: Python :: 3
Classifier: Operating System :: OS Independent
